yased-0.0.3.dist-info/DESCRIPTION.rst
yased-0.0.3.dist-info/RECORD
yased-0.0.3.dist-info/metadata.json
yased-0.0.3.dist-info/METADATA
yased-0.0.3.dist-info/WHEEL
yased-0.0.3.dist-info/top_level.txt
yased/__init__.py
