Metadata-Version: 2.0
Name: yased
Version: 0.0.3
Summary: Yet another simplest events dispatcher
Home-page: https://github.com/pavelpat/yased
Author: Pavel Patrin
Author-email: pavelpat@ya.ru
License: UNKNOWN
Platform: UNKNOWN
